{"answers":[{"acceptanceTime":"2021-09-08T17:18:17Z","answerContent":{"boundingBox":{"boundingBoxes":[{"height":55,"label":"1","left":66,"top":96,"width":11},{"height":55,"label":"1","left":80,"top":96,"width":10}],"inputImageProperties":{"height":231,"width":135}}},"submissionTime":"2021-09-08T17:18:33Z","timeSpentInSeconds":16.0,"workerId":"public.us-east-1.AH7UYMETH5YQ5"},{"acceptanceTime":"2021-09-08T17:19:23Z","answerContent":{"boundingBox":{"boundingBoxes":[{"height":54,"label":"1","left":78,"top":96,"width":12},{"height":55,"label":"1","left":65,"top":95,"width":12}],"inputImageProperties":{"height":231,"width":135}}},"submissionTime":"2021-09-08T17:20:24Z","timeSpentInSeconds":61.0,"workerId":"public.us-east-1.AF1WAWGK3NIHN"},{"acceptanceTime":"2021-09-08T17:23:26Z","answerContent":{"boundingBox":{"boundingBoxes":[{"height":58,"label":"1","left":61,"top":94,"width":19},{"height":56,"label":"1","left":80,"top":95,"width":15}],"inputImageProperties":{"height":231,"width":135}}},"submissionTime":"2021-09-08T17:29:01Z","timeSpentInSeconds":335.0,"workerId":"public.us-east-1.ACANMPNHBVH8Y"},{"acceptanceTime":"2021-09-08T17:25:44Z","answerContent":{"boundingBox":{"boundingBoxes":[{"height":54,"label":"1","left":66,"top":96,"width":12},{"height":54,"label":"1","left":80,"top":96,"width":10}],"inputImageProperties":{"height":231,"width":135}}},"submissionTime":"2021-09-08T17:30:35Z","timeSpentInSeconds":291.0,"workerId":"public.us-east-1.A2AJIPVZWKKZJO"},{"acceptanceTime":"2021-09-08T17:27:25Z","answerContent":{"boundingBox":{"boundingBoxes":[{"height":57,"label":"1","left":66,"top":95,"width":11},{"height":56,"label":"1","left":79,"top":95,"width":11}],"inputImageProperties":{"height":231,"width":135}}},"submissionTime":"2021-09-08T17:30:56Z","timeSpentInSeconds":211.0,"workerId":"public.us-east-1.A3639P754A4OTR"}]}